waffle_window/__init__.py
waffle_window/admin.py
waffle_window/apps.py
waffle_window/management/__init__.py
waffle_window/management/commands/__init__.py
waffle_window/management/commands/sync_flag_membership.py
waffle_window/migrations/0001_initial.py
waffle_window/migrations/__init__.py
waffle_window/models.py
waffle_window-0.1.0.dev0.dist-info/WHEEL
waffle_window-0.1.0.dev0.dist-info/METADATA
waffle_window-0.1.0.dev0.dist-info/RECORD
