Metadata-Version: 2.1
Name: waffle-window
Version: 0.1.0.dev0
Summary: Django app for managing user groups and django-waffle flags.
Home-page: https://github.com/yunojuno/django-waffle-window
License: MIT
Author: YunoJuno
Author-email: code@yunojuno.com
Maintainer: YunoJuno
Maintainer-email: code@yunojuno.com
Requires-Python: >=3.7,<4.0
Classifier: Environment :: Web Environment
Classifier: Framework :: Django :: 2.2
Classifier: Framework :: Django :: 3.0
Classifier: License :: OSI Approved :: MIT License
Classifier: Operating System :: OS Independent
Classifier: Programming Language :: Python :: 3
Classifier: Programming Language :: Python :: 3 :: Only
Classifier: Programming Language :: Python :: 3.7
Classifier: Programming Language :: Python :: 3.8
Requires-Dist: django (>=2.2,<4.0)
Requires-Dist: django-waffle (>=0.19.0,<0.20.0)
Project-URL: Repository, https://github.com/yunojuno/django-waffle-window
